chameli/__init__.py
chameli/config.py
chameli/dateutils.py
chameli/europeanoptions.py
chameli/interactions.py
chameli/miscutils.py
chameli/config/config_sample.yaml
chameli-0.1.10.dist-info/METADATA
chameli-0.1.10.dist-info/WHEEL
chameli-0.1.10.dist-info/top_level.txt
chameli-0.1.10.dist-info/RECORD
