Metadata-Version: 2.4
Name: chameli
Version: 0.1.10
Summary: A lightweight Python library for python utilities for holidays, dates, options and other tools
Author-email: Pankaj Sharma <sharma.pankaj.kumar@gmail.com>
License-Expression: MIT
Project-URL: homepage, https://bitbucket.org/incurrency/chameli
Project-URL: repository, https://bitbucket.org/incurrency/chameli
Requires-Dist: numpy==1.26.4
Requires-Dist: pandas==2.2.3
Requires-Dist: scikit-learn==1.5.0
Requires-Dist: scipy==1.11.4
Requires-Dist: pyyaml==6.0
Requires-Dist: pyreadr==0.5.0
Requires-Dist: rpy2==3.5.16
Requires-Dist: pytz==2024.1
Requires-Dist: selenium==4.0.0
Requires-Dist: requests==2.32.3
Requires-Dist: psutil==7.0.0
Requires-Dist: scp==0.15.0
Requires-Dist: paramiko==3.5.1
Requires-Dist: mitmproxy==12.2.1
